{
    "playlist_info": {
        "name": "Asports Auto Update Playlist",
        "telegram": "https://t.me/livesportsplay",
        "owner": "Md Sohanur Rahman Hady",
        "last_update_time": "09:00:50 AM 26-04-2026"
    },
    "live_matches": [
        {
            "match_id": 1629489621,
            "sport_name": "MMA",
            "sport_id": 17,
            "slug": "sterling-vs-zalal-1629489621",
            "title": "STERLING vs ZALAL",
            "status": "LIVE",
            "league": {
                "league_name": "UFC FIGHT NIGHT",
                "league_logo": ""
            },
            "venue": "TBA",
            "teams": {
                "home_name": "Unknown",
                "away_name": "Unknown",
                "combined_logo": "https://static.vecteezy.com/system/resources/previews/016/314/808/original/transparent-live-transparent-live-icon-free-png.png"
            },
            "timing": {
                "start_time_timestamp": 1777161600,
                "start_time_local": "26 Apr 2026, 06:00 AM"
            },
            "streams": [
                {
                    "server_name": "53768",
                    "play_url": "https://livecdn-bp-iptv.linewgen.xyz/live_abr/53768_hd/index.m3u8?is_vip=false&token=6f055cace5caf84daf522680c80d163b5f6465e0&x-sign=5f1b146020da16a0d3169503fd9057bc&x-time=1777172400",
                    "is_new_format": false,
                    "required_referer": ""
                },
                {
                    "server_name": "161357",
                    "play_url": "https://livecdn-bp-iptv.linewgen.xyz/live_abr/161357_hd/index.m3u8?is_vip=false&token=6f055cace5caf84daf522680c80d163b5f6465e0&x-sign=22224719ed44e304d168cf6a87531aad&x-time=1777172400",
                    "is_new_format": false,
                    "required_referer": ""
                }
            ]
        },
        {
            "match_id": 1629489622,
            "sport_name": "Auto Racing",
            "sport_id": 15,
            "slug": "autopolis-free-practice-2-1629489622",
            "title": "Autopolis - Free Practice 2",
            "status": "LIVE",
            "league": {
                "league_name": "Super Formula",
                "league_logo": ""
            },
            "venue": "TBA",
            "teams": {
                "home_name": "Unknown",
                "away_name": "Unknown",
                "combined_logo": "https://static.vecteezy.com/system/resources/previews/016/314/808/original/transparent-live-transparent-live-icon-free-png.png"
            },
            "timing": {
                "start_time_timestamp": 1777164000,
                "start_time_local": "26 Apr 2026, 06:40 AM"
            },
            "streams": [
                {
                    "server_name": "2",
                    "play_url": "https://livecdn-bp-livestream.linewgen.xyz/stream/2/chunks.m3u8?is_vip=false&token=6f055cace5caf84daf522680c80d163b5f6465e0&x-sign=524b980c37be3a081a4c3f74d61293d3&x-time=1777172400",
                    "is_new_format": false,
                    "required_referer": ""
                }
            ]
        },
        {
            "match_id": 1492611,
            "sport_name": "Football",
            "sport_id": 1,
            "slug": "toluca-vs-leon-1492611",
            "title": "Toluca vs Leon",
            "status": "LIVE",
            "league": {
                "league_name": "Liga MX",
                "league_logo": ""
            },
            "venue": "TBA",
            "teams": {
                "home_name": "Toluca",
                "away_name": "Leon",
                "combined_logo": "https://raw.githubusercontent.com/srhady/axsports/main/bing_posters/Toluca%20VS%20Leon%20%20Liga%20MX.jpg"
            },
            "timing": {
                "start_time_timestamp": 1777165500,
                "start_time_local": "26 Apr 2026, 07:05 AM"
            },
            "streams": [
                {
                    "server_name": "274860",
                    "play_url": "https://livecdn-bp-iptv.linewgen.xyz/live_abr/274860_hd/index.m3u8?is_vip=false&token=6f055cace5caf84daf522680c80d163b5f6465e0&x-sign=f68b4bee5ce0cfa72b48412aaa25b2cf&x-time=1777172400",
                    "is_new_format": false,
                    "required_referer": ""
                }
            ]
        },
        {
            "match_id": 1629489624,
            "sport_name": "Rugby",
            "sport_id": 18,
            "slug": "highlanders-vs-moana-pasifika-1629489624",
            "title": "Highlanders vs Moana Pasifika",
            "status": "LIVE",
            "league": {
                "league_name": "Super Rugby Pacific",
                "league_logo": ""
            },
            "venue": "TBA",
            "teams": {
                "home_name": "Unknown",
                "away_name": "Moana Pasifika",
                "combined_logo": "https://static.vecteezy.com/system/resources/previews/016/314/808/original/transparent-live-transparent-live-icon-free-png.png"
            },
            "timing": {
                "start_time_timestamp": 1777168800,
                "start_time_local": "26 Apr 2026, 08:00 AM"
            },
            "streams": [
                {
                    "server_name": "18",
                    "play_url": "https://livecdn-bp-livestream.linewgen.xyz/stream/18/chunks.m3u8?is_vip=false&token=6f055cace5caf84daf522680c80d163b5f6465e0&x-sign=e78b760a696257a7407cf8a203550759&x-time=1777172400",
                    "is_new_format": false,
                    "required_referer": ""
                }
            ]
        },
        {
            "match_id": 1492613,
            "sport_name": "Football",
            "sport_id": 1,
            "slug": "fc-juarez-vs-atletico-san-luis-1492613",
            "title": "FC Juarez vs Atletico San Luis",
            "status": "LIVE",
            "league": {
                "league_name": "Liga MX",
                "league_logo": ""
            },
            "venue": "TBA",
            "teams": {
                "home_name": "FC Juarez",
                "away_name": "Atletico San Luis",
                "combined_logo": "https://raw.githubusercontent.com/srhady/axsports/main/bing_posters/FC%20Juarez%20VS%20Atletico%20San%20Luis%20%20Liga%20MX.jpg"
            },
            "timing": {
                "start_time_timestamp": 1777172400,
                "start_time_local": "26 Apr 2026, 09:00 AM"
            },
            "streams": [
                {
                    "server_name": "1",
                    "play_url": "https://livecdn-bp-livestream.linewgen.xyz/stream/1/chunks.m3u8?is_vip=false&token=6f055cace5caf84daf522680c80d163b5f6465e0&x-sign=aff56fee4c4c1da018914bf449773cd7&x-time=1777172400",
                    "is_new_format": false,
                    "required_referer": ""
                }
            ]
        },
        {
            "match_id": 1492612,
            "sport_name": "Football",
            "sport_id": 1,
            "slug": "club-america-vs-atlas-1492612",
            "title": "Club America vs Atlas",
            "status": "LIVE",
            "league": {
                "league_name": "Liga MX",
                "league_logo": ""
            },
            "venue": "TBA",
            "teams": {
                "home_name": "Club America",
                "away_name": "Atlas",
                "combined_logo": "https://raw.githubusercontent.com/srhady/axsports/main/bing_posters/Club%20America%20VS%20Atlas%20%20Liga%20MX.jpg"
            },
            "timing": {
                "start_time_timestamp": 1777173000,
                "start_time_local": "26 Apr 2026, 09:10 AM"
            },
            "streams": [
                {
                    "server_name": "274860",
                    "play_url": "https://livecdn-bp-iptv.linewgen.xyz/live_abr/274860_hd/index.m3u8?is_vip=false&token=6f055cace5caf84daf522680c80d163b5f6465e0&x-sign=f68b4bee5ce0cfa72b48412aaa25b2cf&x-time=1777172400",
                    "is_new_format": false,
                    "required_referer": ""
                }
            ]
        }
    ],
    "total_upcoming_matches": 23,
    "upcoming_matches": [
        {
            "match_id": 1629489626,
            "sport_name": "Baseball",
            "sport_id": 12,
            "title": "Orix Buffaloes vs Hokkaido Nippon-Ham Fighters",
            "slug": "orix-buffaloes-vs-hokkaido-nippon-ham-fighters-1629489626",
            "status": "NS",
            "league": {
                "league_name": "NPB",
                "league_logo": ""
            },
            "venue": "TBA",
            "teams": {
                "home_name": "ORIX Buffaloes",
                "away_name": "Hokkaido Nippon-Ham Fighters",
                "combined_logo": "https://raw.githubusercontent.com/srhady/axsports/main/bing_posters/ORIX%20Buffaloes%20VS%20Hokkaido%20Nippon-Ham%20Fighters%20%20NPB.jpg"
            },
            "timing": {
                "start_time_timestamp": 1777176000,
                "start_time_local": "26 Apr 2026, 10:00 AM",
                "countdown_seconds": null
            }
        },
        {
            "match_id": 1629489630,
            "sport_name": "Baseball",
            "sport_id": 12,
            "title": "Chunichi Dragons vs Tokyo Yakult Swallows",
            "slug": "chunichi-dragons-vs-tokyo-yakult-swallows-1629489630",
            "status": "NS",
            "league": {
                "league_name": "NPB",
                "league_logo": ""
            },
            "venue": "TBA",
            "teams": {
                "home_name": "Chunichi Dragons",
                "away_name": "Tokyo Yakult Swallows",
                "combined_logo": "https://raw.githubusercontent.com/srhady/axsports/main/bing_posters/Chunichi%20Dragons%20VS%20Tokyo%20Yakult%20Swallows%20%20NPB.jpg"
            },
            "timing": {
                "start_time_timestamp": 1777177800,
                "start_time_local": "26 Apr 2026, 10:30 AM",
                "countdown_seconds": null
            }
        },
        {
            "match_id": 1469710,
            "sport_name": "Football",
            "sport_id": 1,
            "title": "Sydney vs Auckland",
            "slug": "sydney-vs-auckland-1469710",
            "status": "NS",
            "league": {
                "league_name": "A-League",
                "league_logo": ""
            },
            "venue": "TBA",
            "teams": {
                "home_name": "Sydney",
                "away_name": "Auckland",
                "combined_logo": "https://raw.githubusercontent.com/srhady/axsports/main/bing_posters/Sydney%20VS%20Auckland%20%20A-League.jpg"
            },
            "timing": {
                "start_time_timestamp": 1777179600,
                "start_time_local": "26 Apr 2026, 11:00 AM",
                "countdown_seconds": null
            }
        },
        {
            "match_id": 1629489633,
            "sport_name": "Baseball",
            "sport_id": 12,
            "title": "Yokohama DeNA BayStars vs Yomiuri Giants",
            "slug": "yokohama-dena-baystars-vs-yomiuri-giants-1629489633",
            "status": "NS",
            "league": {
                "league_name": "NPB",
                "league_logo": ""
            },
            "venue": "TBA",
            "teams": {
                "home_name": "YOKOHAMA DeNA BAYSTARS",
                "away_name": "Yomiuri Giants",
                "combined_logo": "https://static.vecteezy.com/system/resources/previews/016/314/808/original/transparent-live-transparent-live-icon-free-png.png"
            },
            "timing": {
                "start_time_timestamp": 1777179600,
                "start_time_local": "26 Apr 2026, 11:00 AM",
                "countdown_seconds": null
            }
        },
        {
            "match_id": 1629489632,
            "sport_name": "Baseball",
            "sport_id": 12,
            "title": "Hanshin Tigers vs Hiroshima Toyo Carp",
            "slug": "hanshin-tigers-vs-hiroshima-toyo-carp-1629489632",
            "status": "NS",
            "league": {
                "league_name": "NPB",
                "league_logo": ""
            },
            "venue": "TBA",
            "teams": {
                "home_name": "Hanshin Tigers",
                "away_name": "Hiroshima Toyo Carp",
                "combined_logo": "https://raw.githubusercontent.com/srhady/axsports/main/bing_posters/Hanshin%20Tigers%20VS%20Hiroshima%20Toyo%20Carp%20%20NPB.jpg"
            },
            "timing": {
                "start_time_timestamp": 1777179600,
                "start_time_local": "26 Apr 2026, 11:00 AM",
                "countdown_seconds": null
            }
        },
        {
            "match_id": 1506953,
            "sport_name": "Football",
            "sport_id": 1,
            "title": "Jeonbuk Motors vs Pohang Steelers",
            "slug": "jeonbuk-motors-vs-pohang-steelers-1506953",
            "status": "NS",
            "league": {
                "league_name": "K League 1",
                "league_logo": ""
            },
            "venue": "TBA",
            "teams": {
                "home_name": "Jeonbuk Motors",
                "away_name": "Pohang Steelers",
                "combined_logo": "https://raw.githubusercontent.com/srhady/axsports/main/bing_posters/Jeonbuk%20Motors%20VS%20Pohang%20Steelers%20%20K%20League%201.jpg"
            },
            "timing": {
                "start_time_timestamp": 1777179600,
                "start_time_local": "26 Apr 2026, 11:00 AM",
                "countdown_seconds": null
            }
        },
        {
            "match_id": 1629489634,
            "sport_name": "Football",
            "sport_id": 1,
            "title": "Adelaide Crows vs Brisbane Lions",
            "slug": "adelaide-crows-vs-brisbane-lions-1629489634",
            "status": "NS",
            "league": {
                "league_name": "Unknown League",
                "league_logo": ""
            },
            "venue": "TBA",
            "teams": {
                "home_name": "Adelaide Crows",
                "away_name": "Brisbane Lions",
                "combined_logo": "https://raw.githubusercontent.com/srhady/axsports/main/bing_posters/Adelaide%20Crows%20VS%20Brisbane%20Lions%20%20AFL%20Premiership.jpg"
            },
            "timing": {
                "start_time_timestamp": 1777180500,
                "start_time_local": "26 Apr 2026, 11:15 AM",
                "countdown_seconds": null
            }
        },
        {
            "match_id": 1629489635,
            "sport_name": "Auto Racing",
            "sport_id": 15,
            "title": "Autopolis - Race",
            "slug": "autopolis-race-1629489635",
            "status": "NS",
            "league": {
                "league_name": "Super Formula",
                "league_logo": ""
            },
            "venue": "TBA",
            "teams": {
                "home_name": "Unknown",
                "away_name": "Unknown",
                "combined_logo": "https://static.vecteezy.com/system/resources/previews/016/314/808/original/transparent-live-transparent-live-icon-free-png.png"
            },
            "timing": {
                "start_time_timestamp": 1777181400,
                "start_time_local": "26 Apr 2026, 11:30 AM",
                "countdown_seconds": null
            }
        },
        {
            "match_id": 1629489636,
            "sport_name": "Rugby",
            "sport_id": 18,
            "title": "Chiefs vs Fijian Drua",
            "slug": "chiefs-vs-fijian-drua-1629489636",
            "status": "NS",
            "league": {
                "league_name": "Super Rugby Pacific",
                "league_logo": ""
            },
            "venue": "TBA",
            "teams": {
                "home_name": "Chiefs",
                "away_name": "Fijian Drua",
                "combined_logo": "https://raw.githubusercontent.com/srhady/axsports/main/bing_posters/Chiefs%20VS%20Fijian%20Drua%20%20Super%20Rugby%20Pacific.jpg"
            },
            "timing": {
                "start_time_timestamp": 1777185000,
                "start_time_local": "26 Apr 2026, 12:30 PM",
                "countdown_seconds": null
            }
        },
        {
            "match_id": 1629489637,
            "sport_name": "Auto Racing",
            "sport_id": 15,
            "title": "Red Bull Ring | Qualifying 2",
            "slug": "red-bull-ring-or-qualifying-2-1629489637",
            "status": "NS",
            "league": {
                "league_name": "Deutsche Tourenwagen Masters",
                "league_logo": ""
            },
            "venue": "TBA",
            "teams": {
                "home_name": "Unknown",
                "away_name": "Unknown",
                "combined_logo": "https://static.vecteezy.com/system/resources/previews/016/314/808/original/transparent-live-transparent-live-icon-free-png.png"
            },
            "timing": {
                "start_time_timestamp": 1777188600,
                "start_time_local": "26 Apr 2026, 01:30 PM",
                "countdown_seconds": null
            }
        },
        {
            "match_id": 1469711,
            "sport_name": "Football",
            "sport_id": 1,
            "title": "Melbourne City vs Adelaide United",
            "slug": "melbourne-city-vs-adelaide-united-1469711",
            "status": "NS",
            "league": {
                "league_name": "A-League",
                "league_logo": ""
            },
            "venue": "TBA",
            "teams": {
                "home_name": "Melbourne City",
                "away_name": "Adelaide United",
                "combined_logo": "https://raw.githubusercontent.com/srhady/axsports/main/bing_posters/Melbourne%20City%20VS%20Adelaide%20United%20%20A-League.jpg"
            },
            "timing": {
                "start_time_timestamp": 1777188600,
                "start_time_local": "26 Apr 2026, 01:30 PM",
                "countdown_seconds": null
            }
        },
        {
            "match_id": 1629489638,
            "sport_name": "Tennis",
            "sport_id": 2,
            "title": "Mutua Madrid Open: Day 6",
            "slug": "mutua-madrid-open-day-6-1629489638",
            "status": "NS",
            "league": {
                "league_name": "WTA 1000",
                "league_logo": ""
            },
            "venue": "TBA",
            "teams": {
                "home_name": "Unknown",
                "away_name": "Unknown",
                "combined_logo": "https://static.vecteezy.com/system/resources/previews/016/314/808/original/transparent-live-transparent-live-icon-free-png.png"
            },
            "timing": {
                "start_time_timestamp": 1777194000,
                "start_time_local": "26 Apr 2026, 03:00 PM",
                "countdown_seconds": null
            }
        },
        {
            "match_id": 1629489639,
            "sport_name": "Cycling",
            "sport_id": 20,
            "title": "Tour of Turkey, Stage 1",
            "slug": "tour-of-turkey-stage-1-1629489639",
            "status": "NS",
            "league": {
                "league_name": "UCI Pro Series",
                "league_logo": ""
            },
            "venue": "TBA",
            "teams": {
                "home_name": "Unknown",
                "away_name": "Unknown",
                "combined_logo": "https://static.vecteezy.com/system/resources/previews/016/314/808/original/transparent-live-transparent-live-icon-free-png.png"
            },
            "timing": {
                "start_time_timestamp": 1777195800,
                "start_time_local": "26 Apr 2026, 03:30 PM",
                "countdown_seconds": null
            }
        },
        {
            "match_id": 1398244,
            "sport_name": "Football",
            "sport_id": 1,
            "title": "Lusitânia Lourosa vs Pacos Ferreira",
            "slug": "lusitania-lourosa-vs-pacos-ferreira-1398244",
            "status": "NS",
            "league": {
                "league_name": "Segunda Liga",
                "league_logo": ""
            },
            "venue": "TBA",
            "teams": {
                "home_name": "Lusitânia Lourosa",
                "away_name": "Pacos Ferreira",
                "combined_logo": "https://raw.githubusercontent.com/srhady/axsports/main/bing_posters/Lusit%C3%A2nia%20Lourosa%20VS%20Pacos%20Ferreira%20%20Segunda%20Liga.jpg"
            },
            "timing": {
                "start_time_timestamp": 1777197600,
                "start_time_local": "26 Apr 2026, 04:00 PM",
                "countdown_seconds": null
            }
        },
        {
            "match_id": 1380652,
            "sport_name": "Football",
            "sport_id": 1,
            "title": "Wisla Plock vs Radomiak Radom",
            "slug": "wisla-plock-vs-radomiak-radom-1380652",
            "status": "NS",
            "league": {
                "league_name": "Ekstraklasa",
                "league_logo": ""
            },
            "venue": "TBA",
            "teams": {
                "home_name": "Wisla Plock",
                "away_name": "Radomiak Radom",
                "combined_logo": "https://raw.githubusercontent.com/srhady/axsports/main/bing_posters/Wisla%20Plock%20VS%20Radomiak%20Radom%20%20Ekstraklasa.jpg"
            },
            "timing": {
                "start_time_timestamp": 1777198500,
                "start_time_local": "26 Apr 2026, 04:15 PM",
                "countdown_seconds": null
            }
        },
        {
            "match_id": 1378196,
            "sport_name": "Football",
            "sport_id": 1,
            "title": "Fiorentina vs Sassuolo",
            "slug": "fiorentina-vs-sassuolo-1378196",
            "status": "NS",
            "league": {
                "league_name": "Serie A",
                "league_logo": ""
            },
            "venue": "TBA",
            "teams": {
                "home_name": "Fiorentina",
                "away_name": "Sassuolo",
                "combined_logo": "https://raw.githubusercontent.com/srhady/axsports/main/bing_posters/Fiorentina%20VS%20Sassuolo%20%20Serie%20A.jpg"
            },
            "timing": {
                "start_time_timestamp": 1777199400,
                "start_time_local": "26 Apr 2026, 04:30 PM",
                "countdown_seconds": null
            }
        },
        {
            "match_id": 1417315,
            "sport_name": "Football",
            "sport_id": 1,
            "title": "Tottenham Hotspur W vs Manchester United W",
            "slug": "tottenham-hotspur-w-vs-manchester-united-w-1417315",
            "status": "NS",
            "league": {
                "league_name": "FA WSL",
                "league_logo": ""
            },
            "venue": "TBA",
            "teams": {
                "home_name": "Tottenham Hotspur W",
                "away_name": "Manchester United W",
                "combined_logo": "https://static.vecteezy.com/system/resources/previews/016/314/808/original/transparent-live-transparent-live-icon-free-png.png"
            },
            "timing": {
                "start_time_timestamp": 1777201200,
                "start_time_local": "26 Apr 2026, 05:00 PM",
                "countdown_seconds": null
            }
        },
        {
            "match_id": 1417313,
            "sport_name": "Football",
            "sport_id": 1,
            "title": "Everton W vs Chelsea W",
            "slug": "everton-w-vs-chelsea-w-1417313",
            "status": "NS",
            "league": {
                "league_name": "FA WSL",
                "league_logo": ""
            },
            "venue": "TBA",
            "teams": {
                "home_name": "Everton W",
                "away_name": "Chelsea W",
                "combined_logo": "https://raw.githubusercontent.com/srhady/axsports/main/bing_posters/Everton%20W%20VS%20Chelsea%20W%20%20FA%20WSL.jpg"
            },
            "timing": {
                "start_time_timestamp": 1777201200,
                "start_time_local": "26 Apr 2026, 05:00 PM",
                "countdown_seconds": null
            }
        },
        {
            "match_id": 1387083,
            "sport_name": "Football",
            "sport_id": 1,
            "title": "Coventry vs Wrexham",
            "slug": "coventry-vs-wrexham-1387083",
            "status": "NS",
            "league": {
                "league_name": "Championship",
                "league_logo": ""
            },
            "venue": "TBA",
            "teams": {
                "home_name": "Coventry",
                "away_name": "Wrexham",
                "combined_logo": "https://raw.githubusercontent.com/srhady/axsports/main/bing_posters/Coventry%20VS%20Wrexham%20%20Championship.jpg"
            },
            "timing": {
                "start_time_timestamp": 1777201200,
                "start_time_local": "26 Apr 2026, 05:00 PM",
                "countdown_seconds": null
            }
        },
        {
            "match_id": 1417310,
            "sport_name": "Football",
            "sport_id": 1,
            "title": "London City Lionesses vs Leicester City WFC",
            "slug": "london-city-lionesses-vs-leicester-city-wfc-1417310",
            "status": "NS",
            "league": {
                "league_name": "FA WSL",
                "league_logo": ""
            },
            "venue": "TBA",
            "teams": {
                "home_name": "London City Lionesses",
                "away_name": "Leicester City WFC",
                "combined_logo": "https://raw.githubusercontent.com/srhady/axsports/main/bing_posters/London%20City%20Lionesses%20VS%20Leicester%20City%20WFC%20%20FA%20WSL.jpg"
            },
            "timing": {
                "start_time_timestamp": 1777201200,
                "start_time_local": "26 Apr 2026, 05:00 PM",
                "countdown_seconds": null
            }
        },
        {
            "match_id": 1394402,
            "sport_name": "Football",
            "sport_id": 1,
            "title": "FC Viktoria Köln vs Energie Cottbus",
            "slug": "fc-viktoria-koln-vs-energie-cottbus-1394402",
            "status": "NS",
            "league": {
                "league_name": "3. Liga",
                "league_logo": ""
            },
            "venue": "TBA",
            "teams": {
                "home_name": "FC Viktoria Köln",
                "away_name": "Energie Cottbus",
                "combined_logo": "https://raw.githubusercontent.com/srhady/axsports/main/bing_posters/FC%20Viktoria%20K%C3%B6ln%20VS%20Energie%20Cottbus%20%203.%20Liga.jpg"
            },
            "timing": {
                "start_time_timestamp": 1777203000,
                "start_time_local": "26 Apr 2026, 05:30 PM",
                "countdown_seconds": null
            }
        },
        {
            "match_id": 1388891,
            "sport_name": "Football",
            "sport_id": 1,
            "title": "SC Paderborn 07 vs FC Schalke 04",
            "slug": "sc-paderborn-07-vs-fc-schalke-04-1388891",
            "status": "NS",
            "league": {
                "league_name": "2. Bundesliga",
                "league_logo": ""
            },
            "venue": "TBA",
            "teams": {
                "home_name": "SC Paderborn 07",
                "away_name": "FC Schalke 04",
                "combined_logo": "https://raw.githubusercontent.com/srhady/axsports/main/bing_posters/SC%20Paderborn%2007%20VS%20FC%20Schalke%2004%20%202.%20Bundesliga.jpg"
            },
            "timing": {
                "start_time_timestamp": 1777203000,
                "start_time_local": "26 Apr 2026, 05:30 PM",
                "countdown_seconds": null
            }
        },
        {
            "match_id": 1388884,
            "sport_name": "Football",
            "sport_id": 1,
            "title": "VfL Bochum vs SpVgg Greuther Fürth",
            "slug": "vfl-bochum-vs-spvgg-greuther-furth-1388884",
            "status": "NS",
            "league": {
                "league_name": "2. Bundesliga",
                "league_logo": ""
            },
            "venue": "TBA",
            "teams": {
                "home_name": "VfL Bochum",
                "away_name": "SpVgg Greuther Fürth",
                "combined_logo": "https://raw.githubusercontent.com/srhady/axsports/main/bing_posters/VfL%20Bochum%20VS%20SpVgg%20Greuther%20F%C3%BCrth%20%202.%20Bundesliga.jpg"
            },
            "timing": {
                "start_time_timestamp": 1777203000,
                "start_time_local": "26 Apr 2026, 05:30 PM",
                "countdown_seconds": null
            }
        }
    ]
}