{
    "playlist_info": {
        "name": "Asports Auto Update Playlist",
        "telegram": "https://t.me/livesportsplay",
        "owner": "Md Sohanur Rahman Hady",
        "last_update_time": "10:31:14 PM 02-05-2026"
    },
    "live_matches": [
        {
            "match_id": 1629490035,
            "sport_name": "Tennis",
            "sport_id": 2,
            "slug": "mutua-madrid-open-day-12-1629490035",
            "title": "Mutua Madrid Open: Day 12",
            "status": "LIVE",
            "league": {
                "league_name": "Unknown League",
                "league_logo": ""
            },
            "venue": "TBA",
            "teams": {
                "home_name": "Unknown",
                "away_name": "Unknown",
                "combined_logo": "https://static.vecteezy.com/system/resources/previews/016/314/808/original/transparent-live-transparent-live-icon-free-png.png"
            },
            "timing": {
                "start_time_timestamp": 1777723200,
                "start_time_local": "02 May 2026, 06:00 PM"
            },
            "streams": [
                {
                    "server_name": "4",
                    "play_url": "https://livecdn-bp-livestream.linewgen.xyz/stream/4/chunks.m3u8?is_vip=false&token=5c3a7be1fa2b25693237f8473395d5bfde2ac0b6&x-sign=f67a8a8d2e7b923930ded614ca3902b9&x-time=1777739400",
                    "is_new_format": false,
                    "required_referer": ""
                },
                {
                    "server_name": "147445",
                    "play_url": "https://livecdn-bp-iptv.linewgen.xyz/live_abr/147445/abr.m3u8",
                    "is_new_format": true,
                    "required_referer": "https://iframe.tnewdesign.site/"
                }
            ]
        },
        {
            "match_id": 1391157,
            "sport_name": "Football",
            "sport_id": 1,
            "slug": "valencia-vs-atletico-madrid-1391157",
            "title": "Valencia vs Atletico Madrid",
            "status": "LIVE",
            "league": {
                "league_name": "La Liga",
                "league_logo": ""
            },
            "venue": "TBA",
            "teams": {
                "home_name": "Valencia",
                "away_name": "Atletico Madrid",
                "combined_logo": "https://raw.githubusercontent.com/srhady/axsports/main/bing_posters/Valencia%20VS%20Atletico%20Madrid%20%20La%20Liga%20%5BServer%202%5D.jpg"
            },
            "timing": {
                "start_time_timestamp": 1777731300,
                "start_time_local": "02 May 2026, 08:15 PM"
            },
            "streams": [
                {
                    "server_name": "51328",
                    "play_url": "https://livecdn-bp-iptv.linewgen.xyz/live_abr/51328/abr.m3u8",
                    "is_new_format": true,
                    "required_referer": "https://iframe.tnewdesign.site/"
                },
                {
                    "server_name": "271334",
                    "play_url": "https://livecdn-bp-iptv.linewgen.xyz/live_abr/271334/abr.m3u8",
                    "is_new_format": true,
                    "required_referer": "https://iframe.tnewdesign.site/"
                }
            ]
        },
        {
            "match_id": 1396522,
            "sport_name": "Football",
            "sport_id": 1,
            "slug": "nacional-vs-avs-1396522",
            "title": "Nacional vs AVS",
            "status": "LIVE",
            "league": {
                "league_name": "Primeira Liga",
                "league_logo": ""
            },
            "venue": "TBA",
            "teams": {
                "home_name": "Nacional",
                "away_name": "AVS",
                "combined_logo": "https://raw.githubusercontent.com/srhady/axsports/main/bing_posters/Nacional%20VS%20AVS%20%20Primeira%20Liga%20%5BServer%201%5D.jpg"
            },
            "timing": {
                "start_time_timestamp": 1777732200,
                "start_time_local": "02 May 2026, 08:30 PM"
            },
            "streams": [
                {
                    "server_name": "161358",
                    "play_url": "https://livecdn-bp-iptv.linewgen.xyz/live_abr/161358/abr.m3u8",
                    "is_new_format": true,
                    "required_referer": "https://iframe.tnewdesign.site/"
                }
            ]
        },
        {
            "match_id": 1396516,
            "sport_name": "Football",
            "sport_id": 1,
            "slug": "arouca-vs-santa-clara-1396516",
            "title": "Arouca vs Santa Clara",
            "status": "LIVE",
            "league": {
                "league_name": "Primeira Liga",
                "league_logo": ""
            },
            "venue": "TBA",
            "teams": {
                "home_name": "Arouca",
                "away_name": "Santa Clara",
                "combined_logo": "https://raw.githubusercontent.com/srhady/axsports/main/bing_posters/Arouca%20VS%20Santa%20Clara%20%20Primeira%20Liga%20%5BServer%201%5D.jpg"
            },
            "timing": {
                "start_time_timestamp": 1777732200,
                "start_time_local": "02 May 2026, 08:30 PM"
            },
            "streams": [
                {
                    "server_name": "161357",
                    "play_url": "https://livecdn-bp-iptv.linewgen.xyz/live_abr/161357/abr.m3u8",
                    "is_new_format": true,
                    "required_referer": "https://iframe.tnewdesign.site/"
                }
            ]
        },
        {
            "match_id": 1387984,
            "sport_name": "Football",
            "sport_id": 1,
            "slug": "paris-saint-germain-vs-lorient-1387984",
            "title": "Paris Saint Germain vs Lorient",
            "status": "LIVE",
            "league": {
                "league_name": "Ligue 1",
                "league_logo": ""
            },
            "venue": "TBA",
            "teams": {
                "home_name": "Paris Saint Germain",
                "away_name": "Lorient",
                "combined_logo": "https://raw.githubusercontent.com/srhady/axsports/main/bing_posters/Paris%20Saint%20Germain%20VS%20Lorient%20%20Ligue%201%20%5BServer%201%5D.jpg"
            },
            "timing": {
                "start_time_timestamp": 1777734000,
                "start_time_local": "02 May 2026, 09:00 PM"
            },
            "streams": [
                {
                    "server_name": "6",
                    "play_url": "https://livecdn-bp-livestream.linewgen.xyz/stream/6/chunks.m3u8?is_vip=false&token=5c3a7be1fa2b25693237f8473395d5bfde2ac0b6&x-sign=a3912f88f4cb5c70c0470eb16525c2de&x-time=1777739400",
                    "is_new_format": false,
                    "required_referer": ""
                }
            ]
        },
        {
            "match_id": 1629490472,
            "sport_name": "Auto Racing",
            "sport_id": 15,
            "slug": "miami-grand-prix-2026-1629490472",
            "title": "MIAMI GRAND PRIX 2026",
            "status": "LIVE",
            "league": {
                "league_name": "Formula 1",
                "league_logo": ""
            },
            "venue": "TBA",
            "teams": {
                "home_name": "Unknown",
                "away_name": "Unknown",
                "combined_logo": "https://static.vecteezy.com/system/resources/previews/016/314/808/original/transparent-live-transparent-live-icon-free-png.png"
            },
            "timing": {
                "start_time_timestamp": 1777737000,
                "start_time_local": "02 May 2026, 09:50 PM"
            },
            "streams": [
                {
                    "server_name": "239",
                    "play_url": "https://livecdn-bp-iptv.linewgen.xyz/live_abr/239/abr.m3u8",
                    "is_new_format": true,
                    "required_referer": "https://iframe.tnewdesign.site/"
                }
            ]
        },
        {
            "match_id": 1378206,
            "sport_name": "Football",
            "sport_id": 1,
            "slug": "como-vs-napoli-1378206",
            "title": "Como vs Napoli",
            "status": "LIVE",
            "league": {
                "league_name": "Serie A",
                "league_logo": ""
            },
            "venue": "TBA",
            "teams": {
                "home_name": "Como",
                "away_name": "Napoli",
                "combined_logo": "https://raw.githubusercontent.com/srhady/axsports/main/bing_posters/Como%20VS%20Napoli%20%20Serie%20A%20%5BServer%201%5D.jpg"
            },
            "timing": {
                "start_time_timestamp": 1777737600,
                "start_time_local": "02 May 2026, 10:00 PM"
            },
            "streams": [
                {
                    "server_name": "27",
                    "play_url": "https://livecdn-bp-livestream.linewgen.xyz/stream/27/chunks.m3u8?is_vip=false&token=5c3a7be1fa2b25693237f8473395d5bfde2ac0b6&x-sign=454acb2ec6be3711670497716b60150d&x-time=1777739400",
                    "is_new_format": false,
                    "required_referer": ""
                },
                {
                    "server_name": "54041",
                    "play_url": "https://livecdn-bp-iptv.linewgen.xyz/live_abr/54041/abr.m3u8",
                    "is_new_format": true,
                    "required_referer": "https://iframe.tnewdesign.site/"
                }
            ]
        },
        {
            "match_id": 1629490037,
            "sport_name": "MMA",
            "sport_id": 17,
            "slug": "fight-club-rush-29-1629490037",
            "title": "FIGHT CLUB RUSH 29",
            "status": "LIVE",
            "league": {
                "league_name": "MMA",
                "league_logo": ""
            },
            "venue": "TBA",
            "teams": {
                "home_name": "Unknown",
                "away_name": "Unknown",
                "combined_logo": "https://static.vecteezy.com/system/resources/previews/016/314/808/original/transparent-live-transparent-live-icon-free-png.png"
            },
            "timing": {
                "start_time_timestamp": 1777737600,
                "start_time_local": "02 May 2026, 10:00 PM"
            },
            "streams": [
                {
                    "server_name": "53770",
                    "play_url": "https://livecdn-bp-iptv.linewgen.xyz/live_abr/53770/abr.m3u8",
                    "is_new_format": true,
                    "required_referer": "https://iframe.tnewdesign.site/"
                },
                {
                    "server_name": "5",
                    "play_url": "https://livecdn-bp-livestream.linewgen.xyz/stream/5/chunks.m3u8?is_vip=false&token=5c3a7be1fa2b25693237f8473395d5bfde2ac0b6&x-sign=62db8cdc49b22a60f7c57d74fae7a4ea&x-time=1777739400",
                    "is_new_format": false,
                    "required_referer": ""
                }
            ]
        },
        {
            "match_id": 1536951,
            "sport_name": "Football",
            "sport_id": 1,
            "slug": "charleroi-vs-genk-1536951",
            "title": "Charleroi vs Genk",
            "status": "LIVE",
            "league": {
                "league_name": "Jupiler Pro League",
                "league_logo": ""
            },
            "venue": "TBA",
            "teams": {
                "home_name": "Charleroi",
                "away_name": "Genk",
                "combined_logo": "https://raw.githubusercontent.com/srhady/axsports/main/bing_posters/Charleroi%20VS%20Genk%20%20Jupiler%20Pro%20League%20%5BServer%201%5D.jpg"
            },
            "timing": {
                "start_time_timestamp": 1777738500,
                "start_time_local": "02 May 2026, 10:15 PM"
            },
            "streams": [
                {
                    "server_name": "2",
                    "play_url": "https://livecdn-bp-livestream.linewgen.xyz/stream/2/chunks.m3u8?is_vip=false&token=5c3a7be1fa2b25693237f8473395d5bfde2ac0b6&x-sign=221b93fdf0fe8f162d753568233f57a2&x-time=1777739400",
                    "is_new_format": false,
                    "required_referer": ""
                }
            ]
        },
        {
            "match_id": 1391149,
            "sport_name": "Football",
            "sport_id": 1,
            "slug": "alaves-vs-athletic-club-1391149",
            "title": "Alaves vs Athletic Club",
            "status": "LIVE",
            "league": {
                "league_name": "La Liga",
                "league_logo": ""
            },
            "venue": "TBA",
            "teams": {
                "home_name": "Alaves",
                "away_name": "Athletic Club",
                "combined_logo": "https://raw.githubusercontent.com/srhady/axsports/main/bing_posters/Alaves%20VS%20Athletic%20Club%20%20La%20Liga.jpg"
            },
            "timing": {
                "start_time_timestamp": 1777739400,
                "start_time_local": "02 May 2026, 10:30 PM"
            },
            "streams": [
                {
                    "server_name": "8",
                    "play_url": "https://livecdn-bp-livestream.linewgen.xyz/stream/8/chunks.m3u8?is_vip=false&token=5c3a7be1fa2b25693237f8473395d5bfde2ac0b6&x-sign=c756215a357cd73da8fc15914d2cebf1&x-time=1777739400",
                    "is_new_format": false,
                    "required_referer": ""
                }
            ]
        },
        {
            "match_id": 1397271,
            "sport_name": "Football",
            "sport_id": 1,
            "slug": "sevilla-w-vs-real-madrid-w-1397271",
            "title": "Sevilla W vs Real Madrid W",
            "status": "LIVE",
            "league": {
                "league_name": "Primera División Femenina",
                "league_logo": ""
            },
            "venue": "TBA",
            "teams": {
                "home_name": "Sevilla W",
                "away_name": "Real Madrid W",
                "combined_logo": "https://raw.githubusercontent.com/srhady/axsports/main/bing_posters/Sevilla%20W%20VS%20Real%20Madrid%20W%20%20Primera%20Divisi%C3%B3n%20Femenina.jpg"
            },
            "timing": {
                "start_time_timestamp": 1777739400,
                "start_time_local": "02 May 2026, 10:30 PM"
            },
            "streams": [
                {
                    "server_name": "23",
                    "play_url": "https://livecdn-bp-livestream.linewgen.xyz/stream/23/chunks.m3u8?is_vip=false&token=5c3a7be1fa2b25693237f8473395d5bfde2ac0b6&x-sign=d430171402d70d680a222da828e8320b&x-time=1777739460",
                    "is_new_format": false,
                    "required_referer": ""
                }
            ]
        },
        {
            "match_id": 1379309,
            "sport_name": "Football",
            "sport_id": 1,
            "slug": "arsenal-vs-fulham-1379309",
            "title": "Arsenal vs Fulham",
            "status": "LIVE",
            "league": {
                "league_name": "Premier League",
                "league_logo": ""
            },
            "venue": "TBA",
            "teams": {
                "home_name": "Arsenal",
                "away_name": "Fulham",
                "combined_logo": "https://raw.githubusercontent.com/srhady/axsports/main/bing_posters/Arsenal%20VS%20Fulham%20%20Premier%20League.jpg"
            },
            "timing": {
                "start_time_timestamp": 1777739400,
                "start_time_local": "02 May 2026, 10:30 PM"
            },
            "streams": [
                {
                    "server_name": "18",
                    "play_url": "https://livecdn-bp-livestream.linewgen.xyz/stream/18/chunks.m3u8?is_vip=false&token=5c3a7be1fa2b25693237f8473395d5bfde2ac0b6&x-sign=78ea1f795db1558bec350f19bd98b563&x-time=1777739460",
                    "is_new_format": false,
                    "required_referer": ""
                }
            ]
        },
        {
            "match_id": 1388587,
            "sport_name": "Football",
            "sport_id": 1,
            "slug": "bayer-leverkusen-vs-rb-leipzig-1388587",
            "title": "Bayer Leverkusen vs RB Leipzig",
            "status": "LIVE",
            "league": {
                "league_name": "Bundesliga",
                "league_logo": ""
            },
            "venue": "TBA",
            "teams": {
                "home_name": "Bayer Leverkusen",
                "away_name": "RB Leipzig",
                "combined_logo": "https://raw.githubusercontent.com/srhady/axsports/main/bing_posters/Bayer%20Leverkusen%20VS%20RB%20Leipzig%20%20Bundesliga.jpg"
            },
            "timing": {
                "start_time_timestamp": 1777739400,
                "start_time_local": "02 May 2026, 10:30 PM"
            },
            "streams": [
                {
                    "server_name": "20",
                    "play_url": "https://livecdn-bp-livestream.linewgen.xyz/stream/20/chunks.m3u8?is_vip=false&token=5c3a7be1fa2b25693237f8473395d5bfde2ac0b6&x-sign=749819534804ffe78a162dca8938abe1&x-time=1777739460",
                    "is_new_format": false,
                    "required_referer": ""
                }
            ]
        }
    ],
    "total_upcoming_matches": 12,
    "upcoming_matches": [
        {
            "match_id": 1387980,
            "sport_name": "Football",
            "sport_id": 1,
            "title": "Metz vs Monaco",
            "slug": "metz-vs-monaco-1387980",
            "status": "NS",
            "league": {
                "league_name": "Ligue 1",
                "league_logo": ""
            },
            "venue": "TBA",
            "teams": {
                "home_name": "Metz",
                "away_name": "Monaco",
                "combined_logo": "https://raw.githubusercontent.com/srhady/axsports/main/bing_posters/Metz%20VS%20Monaco%20%20Ligue%201.jpg"
            },
            "timing": {
                "start_time_timestamp": 1777741200,
                "start_time_local": "02 May 2026, 11:00 PM",
                "countdown_seconds": null
            }
        },
        {
            "match_id": 1396519,
            "sport_name": "Football",
            "sport_id": 1,
            "title": "Famalicao vs Benfica",
            "slug": "famalicao-vs-benfica-1396519",
            "status": "NS",
            "league": {
                "league_name": "Primeira Liga",
                "league_logo": ""
            },
            "venue": "TBA",
            "teams": {
                "home_name": "Famalicao",
                "away_name": "Benfica",
                "combined_logo": "https://raw.githubusercontent.com/srhady/axsports/main/bing_posters/Famalicao%20VS%20Benfica%20%20Primeira%20Liga.jpg"
            },
            "timing": {
                "start_time_timestamp": 1777741200,
                "start_time_local": "02 May 2026, 11:00 PM",
                "countdown_seconds": null
            }
        },
        {
            "match_id": 1389402,
            "sport_name": "Football",
            "sport_id": 1,
            "title": "Rodez vs Saint Etienne",
            "slug": "rodez-vs-saint-etienne-1389402",
            "status": "NS",
            "league": {
                "league_name": "Ligue 2",
                "league_logo": ""
            },
            "venue": "TBA",
            "teams": {
                "home_name": "Rodez",
                "away_name": "Saint Etienne",
                "combined_logo": "https://raw.githubusercontent.com/srhady/axsports/main/bing_posters/Rodez%20VS%20Saint%20Etienne%20%20Ligue%202.jpg"
            },
            "timing": {
                "start_time_timestamp": 1777744800,
                "start_time_local": "03 May 2026, 12:00 AM",
                "countdown_seconds": null
            }
        },
        {
            "match_id": 1389398,
            "sport_name": "Football",
            "sport_id": 1,
            "title": "Le Mans vs Reims",
            "slug": "le-mans-vs-reims-1389398",
            "status": "NS",
            "league": {
                "league_name": "Ligue 2",
                "league_logo": ""
            },
            "venue": "TBA",
            "teams": {
                "home_name": "Le Mans",
                "away_name": "Reims",
                "combined_logo": "https://raw.githubusercontent.com/srhady/axsports/main/bing_posters/Le%20Mans%20VS%20Reims%20%20Ligue%202.jpg"
            },
            "timing": {
                "start_time_timestamp": 1777744800,
                "start_time_local": "03 May 2026, 12:00 AM",
                "countdown_seconds": null
            }
        },
        {
            "match_id": 1381146,
            "sport_name": "Football",
            "sport_id": 1,
            "title": "Ajax vs PSV Eindhoven",
            "slug": "ajax-vs-psv-eindhoven-1381146",
            "status": "NS",
            "league": {
                "league_name": "Eredivisie",
                "league_logo": ""
            },
            "venue": "TBA",
            "teams": {
                "home_name": "Ajax",
                "away_name": "PSV Eindhoven",
                "combined_logo": "https://raw.githubusercontent.com/srhady/axsports/main/bing_posters/Ajax%20VS%20PSV%20Eindhoven%20%20Eredivisie.jpg"
            },
            "timing": {
                "start_time_timestamp": 1777744800,
                "start_time_local": "03 May 2026, 12:00 AM",
                "countdown_seconds": null
            }
        },
        {
            "match_id": 1380658,
            "sport_name": "Football",
            "sport_id": 1,
            "title": "Motor Lublin vs Lech Poznan",
            "slug": "motor-lublin-vs-lech-poznan-1380658",
            "status": "NS",
            "league": {
                "league_name": "Ekstraklasa",
                "league_logo": ""
            },
            "venue": "TBA",
            "teams": {
                "home_name": "Motor Lublin",
                "away_name": "Lech Poznan",
                "combined_logo": "https://raw.githubusercontent.com/srhady/axsports/main/bing_posters/Motor%20Lublin%20VS%20Lech%20Poznan%20%20Ekstraklasa.jpg"
            },
            "timing": {
                "start_time_timestamp": 1777745700,
                "start_time_local": "03 May 2026, 12:15 AM",
                "countdown_seconds": null
            }
        },
        {
            "match_id": 1388900,
            "sport_name": "Football",
            "sport_id": 1,
            "title": "FC Schalke 04 vs Fortuna Düsseldorf",
            "slug": "fc-schalke-04-vs-fortuna-dusseldorf-1388900",
            "status": "NS",
            "league": {
                "league_name": "2. Bundesliga",
                "league_logo": ""
            },
            "venue": "TBA",
            "teams": {
                "home_name": "FC Schalke 04",
                "away_name": "Fortuna Düsseldorf",
                "combined_logo": "https://raw.githubusercontent.com/srhady/axsports/main/bing_posters/FC%20Schalke%2004%20VS%20Fortuna%20D%C3%BCsseldorf%20%202.%20Bundesliga.jpg"
            },
            "timing": {
                "start_time_timestamp": 1777746600,
                "start_time_local": "03 May 2026, 12:30 AM",
                "countdown_seconds": null
            }
        },
        {
            "match_id": 1536994,
            "sport_name": "Football",
            "sport_id": 1,
            "title": "St. Truiden vs Union St. Gilloise",
            "slug": "st-truiden-vs-union-st-gilloise-1536994",
            "status": "NS",
            "league": {
                "league_name": "Jupiler Pro League",
                "league_logo": ""
            },
            "venue": "TBA",
            "teams": {
                "home_name": "St. Truiden",
                "away_name": "Union St. Gilloise",
                "combined_logo": "https://raw.githubusercontent.com/srhady/axsports/main/bing_posters/St.%20Truiden%20VS%20Union%20St.%20Gilloise%20%20Jupiler%20Pro%20League.jpg"
            },
            "timing": {
                "start_time_timestamp": 1777747500,
                "start_time_local": "03 May 2026, 12:45 AM",
                "countdown_seconds": null
            }
        },
        {
            "match_id": 1378204,
            "sport_name": "Football",
            "sport_id": 1,
            "title": "Atalanta vs Genoa",
            "slug": "atalanta-vs-genoa-1378204",
            "status": "NS",
            "league": {
                "league_name": "Serie A",
                "league_logo": ""
            },
            "venue": "TBA",
            "teams": {
                "home_name": "Atalanta",
                "away_name": "Genoa",
                "combined_logo": "https://raw.githubusercontent.com/srhady/axsports/main/bing_posters/Atalanta%20VS%20Genoa%20%20Serie%20A.jpg"
            },
            "timing": {
                "start_time_timestamp": 1777747500,
                "start_time_local": "03 May 2026, 12:45 AM",
                "countdown_seconds": null
            }
        },
        {
            "match_id": 1391155,
            "sport_name": "Football",
            "sport_id": 1,
            "title": "Osasuna vs Barcelona",
            "slug": "osasuna-vs-barcelona-1391155",
            "status": "NS",
            "league": {
                "league_name": "La Liga",
                "league_logo": ""
            },
            "venue": "TBA",
            "teams": {
                "home_name": "Osasuna",
                "away_name": "Barcelona",
                "combined_logo": "https://raw.githubusercontent.com/srhady/axsports/main/bing_posters/Osasuna%20VS%20Barcelona%20%20La%20Liga.jpg"
            },
            "timing": {
                "start_time_timestamp": 1777748400,
                "start_time_local": "03 May 2026, 01:00 AM",
                "countdown_seconds": null
            }
        },
        {
            "match_id": 1381150,
            "sport_name": "Football",
            "sport_id": 1,
            "title": "NEC Nijmegen vs Telstar",
            "slug": "nec-nijmegen-vs-telstar-1381150",
            "status": "NS",
            "league": {
                "league_name": "Eredivisie",
                "league_logo": ""
            },
            "venue": "TBA",
            "teams": {
                "home_name": "NEC Nijmegen",
                "away_name": "Telstar",
                "combined_logo": "https://raw.githubusercontent.com/srhady/axsports/main/bing_posters/NEC%20Nijmegen%20VS%20Telstar%20%20Eredivisie.jpg"
            },
            "timing": {
                "start_time_timestamp": 1777748400,
                "start_time_local": "03 May 2026, 01:00 AM",
                "countdown_seconds": null
            }
        },
        {
            "match_id": 1387982,
            "sport_name": "Football",
            "sport_id": 1,
            "title": "Nice vs Lens",
            "slug": "nice-vs-lens-1387982",
            "status": "NS",
            "league": {
                "league_name": "Ligue 1",
                "league_logo": ""
            },
            "venue": "TBA",
            "teams": {
                "home_name": "Nice",
                "away_name": "Lens",
                "combined_logo": "https://raw.githubusercontent.com/srhady/axsports/main/bing_posters/Nice%20VS%20Lens%20%20Ligue%201.jpg"
            },
            "timing": {
                "start_time_timestamp": 1777748700,
                "start_time_local": "03 May 2026, 01:05 AM",
                "countdown_seconds": null
            }
        }
    ]
}